council_scrapers/__init__.py
council_scrapers/base.py
council_scrapers/constants.py
council_scrapers/database.py
council_scrapers/discord_bot.py
council_scrapers/logging_config.py
council_scrapers/main.py
council_scrapers/scrapers/__init__.py
council_scrapers/scrapers/act/__init__.py
council_scrapers/scrapers/nsw/__init__.py
council_scrapers/scrapers/nsw/bayside_nsw.py
council_scrapers/scrapers/nsw/burwood.py
council_scrapers/scrapers/nsw/camden.py
council_scrapers/scrapers/nsw/campbelltown.py
council_scrapers/scrapers/nsw/canada_bay.py
council_scrapers/scrapers/nsw/canterbury_bankstown.py
council_scrapers/scrapers/nsw/cumberland.py
council_scrapers/scrapers/nsw/georges_river.py
council_scrapers/scrapers/nsw/hornsby.py
council_scrapers/scrapers/nsw/hunters_hill.py
council_scrapers/scrapers/nsw/innerwest.py
council_scrapers/scrapers/nsw/kuringgai.py
council_scrapers/scrapers/nsw/lane_cove.py
council_scrapers/scrapers/nsw/liverpool.py
council_scrapers/scrapers/nsw/north_sydney.py
council_scrapers/scrapers/nsw/northern_beaches.py
council_scrapers/scrapers/nsw/parramatta.py
council_scrapers/scrapers/nsw/penrith_city.py
council_scrapers/scrapers/nsw/randwick.py
council_scrapers/scrapers/nsw/ryde.py
council_scrapers/scrapers/nsw/waverley.py
council_scrapers/scrapers/nsw/willoughby.py
council_scrapers/scrapers/nsw/woollahra.py
council_scrapers/scrapers/qld/__init__.py
council_scrapers/scrapers/vic/__init__.py
council_scrapers/scrapers/vic/banyule.py
council_scrapers/scrapers/vic/bayside.py
council_scrapers/scrapers/vic/boroondara.py
council_scrapers/scrapers/vic/darebin.py
council_scrapers/scrapers/vic/glen_eira.py
council_scrapers/scrapers/vic/hobsons_bay.py
council_scrapers/scrapers/vic/kingston.py
council_scrapers/scrapers/vic/manningham.py
council_scrapers/scrapers/vic/maribyrnong.py
council_scrapers/scrapers/vic/melbourne.py
council_scrapers/scrapers/vic/merribek.py
council_scrapers/scrapers/vic/monash.py
council_scrapers/scrapers/vic/moonee_valley.py
council_scrapers-0.1.0.dist-info/METADATA
council_scrapers-0.1.0.dist-info/WHEEL
council_scrapers-0.1.0.dist-info/RECORD
