Metadata-Version: 2.1
Name: council_scrapers
Version: 0.1.0
Summary: 
License: MIT
Author: Jonathan O'Brien
Author-email: jonathan@jonobri.com
Requires-Python: >=3.9,<3.13
Classifier: License :: OSI Approved :: MIT License
Classifier: Programming Language :: Python :: 3
Classifier: Programming Language :: Python :: 3.9
Classifier: Programming Language :: Python :: 3.10
Classifier: Programming Language :: Python :: 3.11
Classifier: Programming Language :: Python :: 3.12
Requires-Dist: beautifulsoup4 (>=4.12.2,<5.0.0)
Requires-Dist: black (>=24.1.1,<25.0.0)
Requires-Dist: discord.py (>=2.3.2,<3.0.0)
Requires-Dist: onnxruntime (>=1.17.0,<2.0.0)
Requires-Dist: pymupdf (>=1.23.20,<2.0.0)
Requires-Dist: pypdf (>=3.17.4,<4.0.0)
Requires-Dist: pytest-timeout (>=2.2.0,<3.0.0)
Requires-Dist: python-dotenv (>=1.0.0,<2.0.0)
Requires-Dist: requests (>=2.31.0,<3.0.0)
Requires-Dist: selenium (>=4.16.0,<5.0.0)
